azure/mgmt/portal/__init__.py
azure/mgmt/portal/_configuration.py
azure/mgmt/portal/_portal.py
azure/mgmt/portal/_version.py
azure/mgmt/portal/aio/__init__.py
azure/mgmt/portal/aio/_configuration.py
azure/mgmt/portal/aio/_portal.py
azure/mgmt/portal/aio/operations/__init__.py
azure/mgmt/portal/aio/operations/_dashboards_operations.py
azure/mgmt/portal/aio/operations/_list_tenant_configuration_violations_operations.py
azure/mgmt/portal/aio/operations/_operations.py
azure/mgmt/portal/aio/operations/_tenant_configurations_operations.py
azure/mgmt/portal/models/__init__.py
azure/mgmt/portal/models/_models.py
azure/mgmt/portal/models/_models_py3.py
azure/mgmt/portal/models/_portal_enums.py
azure/mgmt/portal/operations/__init__.py
azure/mgmt/portal/operations/_dashboards_operations.py
azure/mgmt/portal/operations/_list_tenant_configuration_violations_operations.py
azure/mgmt/portal/operations/_operations.py
azure/mgmt/portal/operations/_tenant_configurations_operations.py
azure_mgmt_portal-1.0.0.dist-info/METADATA
azure_mgmt_portal-1.0.0.dist-info/WHEEL
azure_mgmt_portal-1.0.0.dist-info/top_level.txt
azure_mgmt_portal-1.0.0.dist-info/RECORD
